bw_processing/__init__.py
bw_processing/array_creation.py
bw_processing/constants.py
bw_processing/datapackage.py
bw_processing/errors.py
bw_processing/filesystem.py
bw_processing/indexing.py
bw_processing/io_helpers.py
bw_processing/io_parquet_helpers.py
bw_processing/io_pyarrow_helpers.py
bw_processing/merging.py
bw_processing/proxies.py
bw_processing/unique_fields.py
bw_processing/utils.py
bw_processing/examples/__init__.py
bw_processing/examples/datapackage_2.zip
bw_processing/examples/interfaces.py
bw_processing/examples/parquet_files.py
bw_processing/examples/simple.zip
bw_processing/examples/datapackage_1/another name.indices.parquet
bw_processing/examples/datapackage_1/sa-data-vector-from-dict.data.parquet
bw_processing/examples/datapackage_1/sa-data-vector-from-dict.distributions.parquet
bw_processing/examples/datapackage_1/sa-data-vector-from-dict.flip.parquet
bw_processing/examples/datapackage_1/sa-data-vector-from-dict.indices.parquet
bw_processing/examples/datapackage_1/some name.data.parquet
bw_processing/examples/datapackage_1/some name.flip.parquet
bw_processing/examples/datapackage_1/some name.indices.parquet
bw_processing-1.0.dist-info/LICENSE
bw_processing-1.0.dist-info/METADATA
bw_processing-1.0.dist-info/WHEEL
bw_processing-1.0.dist-info/top_level.txt
bw_processing-1.0.dist-info/RECORD
