Metadata-Version: 2.1
Name: bw_processing
Version: 1.0
Summary: Foo
Author-email: Chris Mutel <cmutel@gmail.com>
Maintainer-email: Chris Mutel <cmutel@gmail.com>
Project-URL: source, https://github.com/brightway-lca/bw_processing
Project-URL: homepage, https://github.com/brightway-lca/bw_processing
Project-URL: tracker, https://github.com/brightway-lca/bw_processing/issues
Classifier: Development Status :: 4 - Beta
Classifier: Programming Language :: Python
Classifier: Programming Language :: Python :: 3
Classifier: Programming Language :: Python :: 3.9
Classifier: Programming Language :: Python :: 3.10
Classifier: Programming Language :: Python :: 3.11
Classifier: Programming Language :: Python :: 3.12
Classifier: Natural Language :: English
Classifier: Operating System :: OS Independent
Classifier: Topic :: Scientific/Engineering
Requires-Python: >=3.9
License-File: LICENSE
Requires-Dist: fsspec
Requires-Dist: morefs
Requires-Dist: numpy
Requires-Dist: pandas
Provides-Extra: testing
Requires-Dist: bw_processing; extra == "testing"
Requires-Dist: pyarrow; extra == "testing"
Requires-Dist: pytest; extra == "testing"
Requires-Dist: pytest-cov; extra == "testing"
Requires-Dist: python-coveralls; extra == "testing"
Provides-Extra: dev
Requires-Dist: build; extra == "dev"
Requires-Dist: pre-commit; extra == "dev"
Requires-Dist: pylint; extra == "dev"
Requires-Dist: pytest; extra == "dev"
Requires-Dist: pytest-cov; extra == "dev"
Requires-Dist: pytest-randomly; extra == "dev"
Requires-Dist: setuptools; extra == "dev"
